thonnycontrib/esp/__init__.py
thonnycontrib/esp/esp32_api_stubs/_boot.py
thonnycontrib/esp/esp32_api_stubs/_onewire.py
thonnycontrib/esp/esp32_api_stubs/_thread.py
thonnycontrib/esp/esp32_api_stubs/_webrepl.py
thonnycontrib/esp/esp32_api_stubs/apa106.py
thonnycontrib/esp/esp32_api_stubs/array.py
thonnycontrib/esp/esp32_api_stubs/binascii.py
thonnycontrib/esp/esp32_api_stubs/btree.py
thonnycontrib/esp/esp32_api_stubs/builtins.py
thonnycontrib/esp/esp32_api_stubs/cmath.py
thonnycontrib/esp/esp32_api_stubs/collections.py
thonnycontrib/esp/esp32_api_stubs/dht.py
thonnycontrib/esp/esp32_api_stubs/ds18x20.py
thonnycontrib/esp/esp32_api_stubs/errno.py
thonnycontrib/esp/esp32_api_stubs/esp.py
thonnycontrib/esp/esp32_api_stubs/esp32.py
thonnycontrib/esp/esp32_api_stubs/flashbdev.py
thonnycontrib/esp/esp32_api_stubs/framebuf.py
thonnycontrib/esp/esp32_api_stubs/gc.py
thonnycontrib/esp/esp32_api_stubs/hashlib.py
thonnycontrib/esp/esp32_api_stubs/heapq.py
thonnycontrib/esp/esp32_api_stubs/inisetup.py
thonnycontrib/esp/esp32_api_stubs/io.py
thonnycontrib/esp/esp32_api_stubs/json.py
thonnycontrib/esp/esp32_api_stubs/machine.py
thonnycontrib/esp/esp32_api_stubs/math.py
thonnycontrib/esp/esp32_api_stubs/micropython.py
thonnycontrib/esp/esp32_api_stubs/neopixel.py
thonnycontrib/esp/esp32_api_stubs/network.py
thonnycontrib/esp/esp32_api_stubs/ntptime.py
thonnycontrib/esp/esp32_api_stubs/onewire.py
thonnycontrib/esp/esp32_api_stubs/os.py
thonnycontrib/esp/esp32_api_stubs/random.py
thonnycontrib/esp/esp32_api_stubs/re.py
thonnycontrib/esp/esp32_api_stubs/select.py
thonnycontrib/esp/esp32_api_stubs/socket.py
thonnycontrib/esp/esp32_api_stubs/ssl.py
thonnycontrib/esp/esp32_api_stubs/struct.py
thonnycontrib/esp/esp32_api_stubs/sys.py
thonnycontrib/esp/esp32_api_stubs/time.py
thonnycontrib/esp/esp32_api_stubs/ubinascii.py
thonnycontrib/esp/esp32_api_stubs/ucollections.py
thonnycontrib/esp/esp32_api_stubs/uctypes.py
thonnycontrib/esp/esp32_api_stubs/uerrno.py
thonny_esp-0.2.dist-info/LICENSE.txt
thonny_esp-0.2.dist-info/METADATA
thonny_esp-0.2.dist-info/WHEEL
thonny_esp-0.2.dist-info/top_level.txt
thonny_esp-0.2.dist-info/RECORD
